pyquickbench/__init__.py
pyquickbench/_benchmark.py
pyquickbench/_defaults.py
pyquickbench/_time_train.py
pyquickbench/_utils.py
pyquickbench-0.2.5.dist-info/licenses/LICENSE
pyquickbench-0.2.5.dist-info/METADATA
pyquickbench-0.2.5.dist-info/WHEEL
pyquickbench-0.2.5.dist-info/top_level.txt
pyquickbench-0.2.5.dist-info/RECORD
