Metadata-Version: 2.4
Name: pyquickbench
Version: 0.2.5
Summary: A pure Pyton tool to perform time and accuracy benchmarks
Author-email: Gabriel Fougeron <gabriel.fougeron@hotmail.fr>
License: BSD 2-Clause License
Project-URL: Homepage, https://gabrielfougeron.github.io/pyquickbench/
Project-URL: Documentation, https://gabrielfougeron.github.io/pyquickbench/
Project-URL: Repository, https://github.com/gabrielfougeron/pyquickbench
Project-URL: Changelog, https://github.com/gabrielfougeron/pyquickbench/releases/
Keywords: Python,benchmark
Classifier: Development Status :: 4 - Beta
Classifier: Programming Language :: Python
Classifier: Programming Language :: Python :: 3
Classifier: Programming Language :: Python :: 3.7
Classifier: Programming Language :: Python :: 3.8
Classifier: Programming Language :: Python :: 3.9
Classifier: Programming Language :: Python :: 3.10
Classifier: Programming Language :: Python :: 3.11
Classifier: Programming Language :: Python :: 3.12
Classifier: Programming Language :: Python :: 3.13
Classifier: License :: OSI Approved :: BSD License
Classifier: Natural Language :: English
Requires-Python: >=3.7
License-File: LICENSE
Requires-Dist: numpy
Requires-Dist: matplotlib
Requires-Dist: tqdm
Requires-Dist: ipywidgets
Provides-Extra: docs
Requires-Dist: Sphinx; extra == "docs"
Requires-Dist: pydata-sphinx-theme; extra == "docs"
Requires-Dist: sphinx-gallery; extra == "docs"
Requires-Dist: sphinx-pyproject; extra == "docs"
Requires-Dist: sphinx-needs; extra == "docs"
Requires-Dist: sphinx-test-reports; extra == "docs"
Requires-Dist: sphinxcontrib-plantuml; extra == "docs"
Requires-Dist: seed-intersphinx-mapping; extra == "docs"
Requires-Dist: myst-parser; extra == "docs"
Requires-Dist: sphinxext-rediraffe; extra == "docs"
Requires-Dist: sphinx-sitemap; extra == "docs"
Requires-Dist: sphinx-design; extra == "docs"
Requires-Dist: sphinx-copybutton; extra == "docs"
Requires-Dist: scipy; extra == "docs"
Requires-Dist: numba; extra == "docs"
Requires-Dist: threadpoolctl; extra == "docs"
Requires-Dist: torch; extra == "docs"
Requires-Dist: torchvision; extra == "docs"
Requires-Dist: torchaudio; extra == "docs"
Provides-Extra: tests
Requires-Dist: attrs; extra == "tests"
Requires-Dist: pytest; extra == "tests"
Requires-Dist: pytest-xdist; extra == "tests"
Dynamic: license-file
